django_clone-5.5.0.dist-info/licenses/LICENSE
model_clone/__init__.py
model_clone/admin.py
model_clone/apps.py
model_clone/mixin.py
model_clone/models.py
model_clone/signals.py
model_clone/utils.py
model_clone/templates/admin/change_form_object_tools.html
model_clone/templates/clone/change_form.html
django_clone-5.5.0.dist-info/METADATA
django_clone-5.5.0.dist-info/WHEEL
django_clone-5.5.0.dist-info/top_level.txt
django_clone-5.5.0.dist-info/RECORD
