Metadata-Version: 2.4
Name: django-clone
Version: 5.5.0
Summary: Create a clone of a django model instance.
Home-page: https://github.com/tj-django/django-clone.git
Author: Tonye Jack
Author-email: jtonye@ymail.com
Maintainer: Tonye Jack
Maintainer-email: jtonye@ymail.com
License: MIT/Apache-2.0
Keywords: django,django-clone,django clone,django object clone,clone-django,model cloning,django instance duplication,django duplication
Classifier: Development Status :: 5 - Production/Stable
Classifier: Intended Audience :: Developers
Classifier: License :: OSI Approved :: MIT License
Classifier: License :: OSI Approved :: Apache Software License
Classifier: Natural Language :: English
Classifier: Topic :: Internet :: WWW/HTTP
Classifier: Operating System :: OS Independent
Classifier: Programming Language :: Python :: 3.6
Classifier: Programming Language :: Python :: 3.7
Classifier: Programming Language :: Python :: 3.8
Classifier: Programming Language :: Python :: 3.9
Classifier: Programming Language :: Python :: 3.10
Classifier: Programming Language :: Python :: 3.11
Classifier: Programming Language :: Python :: Implementation :: CPython
Classifier: Programming Language :: Python :: Implementation :: PyPy
Classifier: Framework :: Django :: 2.0
Classifier: Framework :: Django :: 2.1
Classifier: Framework :: Django :: 2.2
Classifier: Framework :: Django :: 3.0
Classifier: Framework :: Django :: 3.1
Classifier: Framework :: Django :: 3.2
Classifier: Framework :: Django :: 4.0
Classifier: Framework :: Django :: 4.1
Classifier: Framework :: Django :: 4.2
Requires-Python: >=3.6
License-File: LICENSE
Requires-Dist: django
Requires-Dist: conditional>=1.3
Requires-Dist: six
Provides-Extra: development
Requires-Dist: pip-tools; extra == "development"
Requires-Dist: check-manifest; extra == "development"
Requires-Dist: django; extra == "development"
Requires-Dist: conditional>=1.3; extra == "development"
Requires-Dist: six; extra == "development"
Requires-Dist: tox; extra == "development"
Requires-Dist: tox-gh-actions; extra == "development"
Requires-Dist: pluggy>=0.7; extra == "development"
Requires-Dist: mock; extra == "development"
Requires-Dist: unittest-xml-reporting; extra == "development"
Requires-Dist: codacy-coverage; extra == "development"
Requires-Dist: django-migration-fixer; extra == "development"
Requires-Dist: bump2version; extra == "development"
Requires-Dist: readme_renderer[md]; extra == "development"
Requires-Dist: git-changelog; extra == "development"
Provides-Extra: test
Requires-Dist: tox; extra == "test"
Requires-Dist: tox-gh-actions; extra == "test"
Requires-Dist: pluggy>=0.7; extra == "test"
Requires-Dist: mock; extra == "test"
Requires-Dist: unittest-xml-reporting; extra == "test"
Requires-Dist: codacy-coverage; extra == "test"
Requires-Dist: django-migration-fixer; extra == "test"
Provides-Extra: deploy
Requires-Dist: bump2version; extra == "deploy"
Requires-Dist: readme_renderer[md]; extra == "deploy"
Requires-Dist: git-changelog; extra == "deploy"
Dynamic: author
Dynamic: author-email
Dynamic: classifier
Dynamic: description
Dynamic: description-content-type
Dynamic: home-page
Dynamic: keywords
Dynamic: license
Dynamic: license-file
Dynamic: maintainer
Dynamic: maintainer-email
Dynamic: provides-extra
Dynamic: requires-dist
Dynamic: requires-python
Dynamic: summary
